VDP/__init__.py
VDP/layers.py
VDP-0.1.0.dist-info/METADATA
VDP-0.1.0.dist-info/WHEEL
VDP-0.1.0.dist-info/top_level.txt
VDP-0.1.0.dist-info/RECORD
