Metadata-Version: 2.1
Name: VDP
Version: 0.1.0
Summary: Variational Density Propagation (VDP) CNN Layers for TensorFlow
Home-page: https://github.com/dimahdera/PremiUm-CNN-CIFAR10-Tensorflow-2.x
Author: Rohaan Nadeem
Author-email: rohaan.nadeem@fulbrightmail.org
Classifier: Programming Language :: Python :: 3
Classifier: Operating System :: OS Independent
Requires-Python: >=3.6
Requires-Dist: tensorflow
Requires-Dist: numpy
Requires-Dist: matplotlib
Requires-Dist: pandas
Requires-Dist: scipy
Requires-Dist: xlsxwriter
Requires-Dist: wandb
